valueapifrontend/__init__.py
valueapifrontend/app.py
valueapifrontend/main.py
valueapifrontend-0.1.1.dist-info/METADATA
valueapifrontend-0.1.1.dist-info/WHEEL
valueapifrontend-0.1.1.dist-info/entry_points.txt
valueapifrontend-0.1.1.dist-info/RECORD
