Metadata-Version: 2.4
Name: valueapifrontend
Version: 0.1.1
Summary: Add your description here
Author-email: Jonas Blatt <jonas@blatts.de>
Requires-Python: >=3.13
Requires-Dist: click>=8.1.8
Requires-Dist: streamlit>=1.44.0
Requires-Dist: valueapiconnector>=0.1.0
Requires-Dist: watchdog>=6.0.0
